TWT.py
TWT-0.0.2.dist-info/LICENSE.txt
TWT-0.0.2.dist-info/METADATA
TWT-0.0.2.dist-info/WHEEL
TWT-0.0.2.dist-info/top_level.txt
TWT-0.0.2.dist-info/RECORD
