Metadata-Version: 2.1
Name: TWT
Version: 0.0.2
Summary: Dedicated in the SAR
Home-page: https://github.com/UCAS-BigBird/TWT
Author: Hunter-Ou
Author-email: oy199603@qq.com
License: UNKNOWN
Platform: UNKNOWN
Requires-Python: >=3.6
